deep_ocr/__init__.py
deep_ocr/cli.py
deep_ocr/ocr.py
deep_ocr-0.1.1.dist-info/METADATA
deep_ocr-0.1.1.dist-info/WHEEL
deep_ocr-0.1.1.dist-info/entry_points.txt
deep_ocr-0.1.1.dist-info/licenses/LICENSE
deep_ocr-0.1.1.dist-info/RECORD
