Metadata-Version: 2.4
Name: deep-ocr
Version: 0.1.1
Summary: A Python wrapper for DeepSeek-OCR model with easy-to-use API, CPU/GPU support, and Flash Attention optimization
Project-URL: Homepage, https://github.com/Gershonbest/deep-ocr
Project-URL: Repository, https://github.com/Gershonbest/deep-ocr
Project-URL: Documentation, https://github.com/Gershonbest/deep-ocr#readme
Project-URL: Bug Tracker, https://github.com/Gershonbest/deep-ocr/issues
Author-email: Gershon Omoraka <gershblocks@gmail.com>
Maintainer-email: Gershon Omoraka <gershblock@gmail.com>
License-Expression: MIT
License-File: LICENSE
Keywords: ai,computer-vision,deepseek,ocr,text-extraction
Classifier: Development Status :: 4 - Beta
Classifier: Intended Audience :: Developers
Classifier: Operating System :: OS Independent
Classifier: Programming Language :: Python :: 3
Classifier: Programming Language :: Python :: 3.11
Classifier: Programming Language :: Python :: 3.12
Classifier: Topic :: Scientific/Engineering :: Artificial Intelligence
Classifier: Topic :: Software Development :: Libraries :: Python Modules
Requires-Python: >=3.11
Requires-Dist: addict>=2.4.0
Requires-Dist: easydict>=1.13
Requires-Dist: einops>=0.8.1
Requires-Dist: pillow>=10.0.0
Requires-Dist: tokenizers==0.20.3
Requires-Dist: torch==2.6.0
Requires-Dist: torchvision
Requires-Dist: transformers==4.46.3
Provides-Extra: dev
Requires-Dist: black>=23.0.0; extra == 'dev'
Requires-Dist: flake8>=6.0.0; extra == 'dev'
Requires-Dist: isort>=5.12.0; extra == 'dev'
Requires-Dist: mypy>=1.0.0; extra == 'dev'
Requires-Dist: pytest-cov>=4.0.0; extra == 'dev'
Requires-Dist: pytest>=7.0.0; extra == 'dev'
Provides-Extra: flash-attn
Requires-Dist: flash-attn==2.7.3; extra == 'flash-attn'
